barladb/classes.py
barladb/config.py
barladb/db.py
barladb/log_functions.py
barladb-0.2.70.dist-info/METADATA
barladb-0.2.70.dist-info/WHEEL
barladb-0.2.70.dist-info/top_level.txt
barladb-0.2.70.dist-info/RECORD
