Metadata-Version: 2.1
Name: barladb
Version: 0.2.70
Summary: Module for working with JSON file data
Home-page: https://github.com/barlin41k/barladb
Author: barlin41k
Project-URL: Documentation, https://sites.google.com/view/barladb/
Project-URL: GitHub, https://github.com/barlin41k/barladb
